spherov2/__init__.py
spherov2/helper.py
spherov2/scanner.py
spherov2/sphero_edu.py
spherov2/types.py
spherov2/utils.py
spherov2/adapter/bleak_adapter.py
spherov2/adapter/tcp_adapter.py
spherov2/adapter/tcp_consts.py
spherov2/adapter/tcp_server.py
spherov2/commands/__init__.py
spherov2/commands/animatronic.py
spherov2/commands/api_and_shell.py
spherov2/commands/async_.py
spherov2/commands/bootloader.py
spherov2/commands/connection.py
spherov2/commands/core.py
spherov2/commands/drive.py
spherov2/commands/factory_test.py
spherov2/commands/firmware.py
spherov2/commands/io.py
spherov2/commands/power.py
spherov2/commands/sensor.py
spherov2/commands/sphero.py
spherov2/commands/system_info.py
spherov2/commands/system_mode.py
spherov2/controls/__init__.py
spherov2/controls/v1.py
spherov2/controls/v2.py
spherov2/listeners/api_and_shell.py
spherov2/listeners/async_.py
spherov2/listeners/core.py
spherov2/listeners/drive.py
spherov2/listeners/power.py
spherov2/listeners/sensor.py
spherov2/listeners/sphero.py
spherov2/listeners/system_info.py
spherov2/toy/__init__.py
spherov2/toy/bb8.py
spherov2/toy/bb9e.py
spherov2/toy/bolt.py
spherov2/toy/mini.py
spherov2/toy/ollie.py
spherov2/toy/r2d2.py
spherov2/toy/r2q5.py
spherov2/toy/rvr.py
spherov2/toy/sphero.py
spherov2/toy/sprk2.py
spherov2-0.12.dist-info/LICENSE
spherov2-0.12.dist-info/METADATA
spherov2-0.12.dist-info/WHEEL
spherov2-0.12.dist-info/top_level.txt
spherov2-0.12.dist-info/RECORD
