Metadata-Version: 2.1
Name: spherov2
Version: 0.12
Summary: An unofficial Bluetooth low energy library for Sphero toys in Python.
Home-page: https://github.com/artificial-intelligence-class/spherov2.py
Author: Hanbang Wang
Author-email: hanbangw@cis.upenn.edu
License: MIT
Keywords: robotics Sphero toy bluetooth ble
Classifier: Development Status :: 4 - Beta
Classifier: Framework :: Robot Framework :: Library
Classifier: Intended Audience :: Education
Classifier: License :: OSI Approved :: MIT License
Classifier: Operating System :: OS Independent
Classifier: Programming Language :: Python :: 3.7
Classifier: Programming Language :: Python :: 3.8
Requires-Python: >=3.7
License-File: LICENSE
Requires-Dist: numpy
Requires-Dist: transforms3d
